HISTORY.rst
LICENSE
MANIFEST.in
README.rst
dev-requirements.txt
requirements.txt
setup.py
docs/Makefile
docs/conf.py
docs/index.rst
proxy_toggle.egg-info/PKG-INFO
proxy_toggle.egg-info/SOURCES.txt
proxy_toggle.egg-info/dependency_links.txt
proxy_toggle.egg-info/entry_points.txt
proxy_toggle.egg-info/requires.txt
proxy_toggle.egg-info/top_level.txt
proxytoggle/__init__.py
proxytoggle/px.py
tests/test_px.py
tests/test_px.pyc
tests/keyring/.pass
tests/keyring/pubring.gpg
tests/keyring/px.conf
tests/keyring/random_seed
tests/keyring/secring.gpg
tests/keyring/trustdb.gpg